{
    "dataset": {
        "source": "ARG_U1992Y",
        "timespan": "UnDefined",
        "coverage": "Urban",
        "year": 1992,
        "iso3c": "ARG",
        "format": "Unit record",
        "country": "Argentina",
        "measure": "Income"
    },
    "lorenz": {
        "L": [
            7.5459e-05,
            0.00089177,
            0.0020411,
            0.0034365,
            0.0051046,
            0.0070126,
            0.0090169,
            0.011439,
            0.013612,
            0.01707,
            0.018704,
            0.021925,
            0.026163,
            0.027184,
            0.030104,
            0.033184,
            0.036043,
            0.039186,
            0.044274,
            0.046023,
            0.058367,
            0.058367,
            0.058367,
            0.061273,
            0.065022,
            0.070157,
            0.073521,
            0.077647,
            0.082481,
            0.086936,
            0.091869,
            0.09636,
            0.10519,
            0.10617,
            0.11201,
            0.122,
            0.122,
            0.12714,
            0.13258,
            0.14656,
            0.14656,
            0.14994,
            0.15582,
            0.1611,
            0.17172,
            0.17361,
            0.17998,
            0.1865,
            0.1973,
            0.20012,
            0.20741,
            0.21475,
            0.22154,
            0.23951,
            0.23951,
            0.24477,
            0.25191,
            0.25994,
            0.2683,
            0.27728,
            0.28671,
            0.2941,
            0.30368,
            0.31229,
            0.32835,
            0.33164,
            0.34183,
            0.35056,
            0.36229,
            0.37585,
            0.38165,
            0.39295,
            0.40925,
            0.41562,
            0.4267,
            0.43893,
            0.45155,
            0.46796,
            0.47808,
            0.49259,
            0.5064,
            0.52071,
            0.54061,
            0.55085,
            0.5668,
            0.58333,
            0.60124,
            0.62829,
            0.63718,
            0.65713,
            0.67843,
            0.7005,
            0.72604,
            0.75219,
            0.7782,
            0.80693,
            0.83998,
            0.87785,
            0.92597,
            1.0
        ],
        "index": [
            0,
            1,
            2,
            3,
            4,
            5,
            6,
            7,
            8,
            9,
            10,
            11,
            12,
            13,
            14,
            15,
            16,
            17,
            18,
            19,
            20,
            21,
            22,
            23,
            24,
            25,
            26,
            27,
            28,
            29,
            30,
            31,
            32,
            33,
            34,
            35,
            36,
            37,
            38,
            39,
            40,
            41,
            42,
            43,
            44,
            45,
            46,
            47,
            48,
            49,
            50,
            51,
            52,
            53,
            54,
            55,
            56,
            57,
            58,
            59,
            60,
            61,
            62,
            63,
            64,
            65,
            66,
            67,
            68,
            69,
            70,
            71,
            72,
            73,
            74,
            75,
            76,
            77,
            78,
            79,
            80,
            81,
            82,
            83,
            84,
            85,
            86,
            87,
            88,
            89,
            90,
            91,
            92,
            93,
            94,
            95,
            96,
            97,
            98,
            99
        ],
        "p": [
            0.010566,
            0.0205,
            0.030117,
            0.040023,
            0.050032,
            0.060282,
            0.070086,
            0.081029,
            0.09038,
            0.10419,
            0.11043,
            0.12234,
            0.13747,
            0.14107,
            0.15105,
            0.16127,
            0.1704,
            0.18003,
            0.195,
            0.20005,
            0.23331,
            0.23331,
            0.23331,
            0.24082,
            0.25023,
            0.26265,
            0.27054,
            0.28001,
            0.29079,
            0.3005,
            0.31103,
            0.32042,
            0.33827,
            0.34023,
            0.35166,
            0.37076,
            0.37076,
            0.3804,
            0.39038,
            0.41533,
            0.41533,
            0.42124,
            0.43121,
            0.44001,
            0.45718,
            0.46018,
            0.47015,
            0.48006,
            0.49598,
            0.50009,
            0.51052,
            0.52075,
            0.53001,
            0.55398,
            0.55398,
            0.5609,
            0.57004,
            0.58004,
            0.59019,
            0.60083,
            0.61186,
            0.62028,
            0.63097,
            0.64038,
            0.65751,
            0.66097,
            0.67149,
            0.68028,
            0.69181,
            0.70484,
            0.71031,
            0.7207,
            0.7352,
            0.74075,
            0.75008,
            0.76008,
            0.77012,
            0.78273,
            0.79028,
            0.80087,
            0.81067,
            0.82054,
            0.83382,
            0.84048,
            0.85043,
            0.86038,
            0.87078,
            0.88547,
            0.89007,
            0.9,
            0.91011,
            0.92,
            0.93074,
            0.94093,
            0.9504,
            0.96011,
            0.97009,
            0.98008,
            0.99046,
            1.0
        ]
    },
    "dist": {
        "deciles": [
            1.6022,
            2.9983,
            4.07,
            5.1263,
            6.2088,
            7.6524,
            9.4226,
            12.059,
            16.573,
            34.287
        ],
        "Gini": 0.454681,
        "Watt": 0.00524496,
        "MLD": 0.410654,
        "FGT2": 0.00998744,
        "PG": 0.011789,
        "HC": 0.0205003,
        "median_ppp": 387.925
    },
    "sample": {
        "mean_month_lcu": 293.483,
        "effective_pop_wealth": 1300200000.0,
        "month_min": 0.0,
        "mean_month_ppp": 564.542,
        "month_max": 3431.61,
        "month_max_is_ppp": "",
        "month_min_is_ppp": "",
        "N": 2386,
        "effective_pop_wealth_is_ppp": "",
        "effective_pop_N": 12264700.0
    },
    "inputs": {
        "line_month_lcu": 30.0436,
        "line_day_ppp": 1.9,
        "ppp": 2.76838,
        "line_month_ppp": 57.7917
    }
}