{
    "dataset": {
        "source": "PRY_N2001Y",
        "timespan": "UnDefined",
        "coverage": "National",
        "year": 2001,
        "iso3c": "PRY",
        "format": "Unit record",
        "country": "Paraguay",
        "measure": "Income"
    },
    "lorenz": {
        "L": [
            0.00016385,
            0.00067851,
            0.0013145,
            0.0020608,
            0.0029967,
            0.0040722,
            0.0053026,
            0.0065378,
            0.0079004,
            0.0094253,
            0.011058,
            0.012711,
            0.014625,
            0.016506,
            0.018489,
            0.020647,
            0.022923,
            0.025329,
            0.027788,
            0.031073,
            0.03299,
            0.03562,
            0.03839,
            0.041268,
            0.044208,
            0.047224,
            0.050381,
            0.053646,
            0.059373,
            0.060455,
            0.063961,
            0.067766,
            0.071318,
            0.07524,
            0.079156,
            0.083249,
            0.087433,
            0.091753,
            0.096229,
            0.10083,
            0.10561,
            0.11034,
            0.11531,
            0.12045,
            0.12569,
            0.1312,
            0.13764,
            0.1422,
            0.14783,
            0.15336,
            0.15958,
            0.16568,
            0.1731,
            0.17784,
            0.18473,
            0.19084,
            0.19763,
            0.20452,
            0.21165,
            0.21924,
            0.22639,
            0.23397,
            0.242,
            0.24977,
            0.25841,
            0.26619,
            0.27554,
            0.28339,
            0.29211,
            0.30147,
            0.31092,
            0.32052,
            0.33107,
            0.34096,
            0.3514,
            0.36241,
            0.37356,
            0.38534,
            0.39732,
            0.40972,
            0.4226,
            0.43605,
            0.44992,
            0.46444,
            0.48,
            0.4956,
            0.51236,
            0.52963,
            0.54773,
            0.56732,
            0.58805,
            0.6096,
            0.63369,
            0.65962,
            0.68849,
            0.72171,
            0.75695,
            0.80194,
            0.86075,
            1.0
        ],
        "index": [
            0,
            1,
            2,
            3,
            4,
            5,
            6,
            7,
            8,
            9,
            10,
            11,
            12,
            13,
            14,
            15,
            16,
            17,
            18,
            19,
            20,
            21,
            22,
            23,
            24,
            25,
            26,
            27,
            28,
            29,
            30,
            31,
            32,
            33,
            34,
            35,
            36,
            37,
            38,
            39,
            40,
            41,
            42,
            43,
            44,
            45,
            46,
            47,
            48,
            49,
            50,
            51,
            52,
            53,
            54,
            55,
            56,
            57,
            58,
            59,
            60,
            61,
            62,
            63,
            64,
            65,
            66,
            67,
            68,
            69,
            70,
            71,
            72,
            73,
            74,
            75,
            76,
            77,
            78,
            79,
            80,
            81,
            82,
            83,
            84,
            85,
            86,
            87,
            88,
            89,
            90,
            91,
            92,
            93,
            94,
            95,
            96,
            97,
            98,
            99
        ],
        "p": [
            0.010127,
            0.020348,
            0.030418,
            0.040087,
            0.050174,
            0.060278,
            0.070795,
            0.080349,
            0.090055,
            0.10012,
            0.1103,
            0.12003,
            0.13054,
            0.14026,
            0.15001,
            0.16003,
            0.17007,
            0.18016,
            0.19006,
            0.20298,
            0.21035,
            0.22018,
            0.23013,
            0.24015,
            0.25014,
            0.26007,
            0.27006,
            0.28003,
            0.29688,
            0.30002,
            0.31,
            0.3205,
            0.33002,
            0.34022,
            0.35005,
            0.36008,
            0.37004,
            0.38003,
            0.39005,
            0.40005,
            0.41021,
            0.42003,
            0.43007,
            0.44021,
            0.45023,
            0.46052,
            0.47228,
            0.48045,
            0.49043,
            0.50001,
            0.51051,
            0.52059,
            0.53259,
            0.54008,
            0.55076,
            0.56007,
            0.57015,
            0.58005,
            0.59003,
            0.60044,
            0.61005,
            0.62003,
            0.63038,
            0.64015,
            0.65074,
            0.66014,
            0.67119,
            0.68025,
            0.69002,
            0.70022,
            0.71022,
            0.7201,
            0.73059,
            0.74016,
            0.75001,
            0.76006,
            0.77001,
            0.78011,
            0.79006,
            0.80001,
            0.81002,
            0.82014,
            0.83007,
            0.84003,
            0.8503,
            0.86012,
            0.8701,
            0.88005,
            0.89002,
            0.90024,
            0.91029,
            0.92016,
            0.93021,
            0.9401,
            0.95006,
            0.96047,
            0.97001,
            0.98002,
            0.99005,
            1.0
        ]
    },
    "dist": {
        "deciles": [
            0.94076,
            2.0907,
            3.0133,
            4.036,
            5.2542,
            6.5573,
            8.2348,
            10.843,
            15.715,
            43.315
        ],
        "Gini": 0.5483,
        "Watt": 0.055853,
        "MLD": 0.591887,
        "FGT2": 0.0206789,
        "PG": 0.0361536,
        "HC": 0.090671,
        "median_ppp": 231.078
    },
    "sample": {
        "mean_month_lcu": 423862.0,
        "effective_pop_wealth": 1059270000.0,
        "month_min": 0.0,
        "mean_month_ppp": 394.293,
        "month_max": 23298.3,
        "month_max_is_ppp": "(PPP$)",
        "month_min_is_ppp": "(PPP$)",
        "N": 7415,
        "effective_pop_wealth_is_ppp": "(PPP$)",
        "effective_pop_N": 5771480.0
    },
    "inputs": {
        "line_month_lcu": 62125.6,
        "line_day_ppp": 1.9,
        "ppp": 2309.43,
        "line_month_ppp": 57.7917
    }
}